external_user_local/__init__.py
external_user_local/external_user.py
external_user_local-0.0.33.dist-info/METADATA
external_user_local-0.0.33.dist-info/WHEEL
external_user_local-0.0.33.dist-info/top_level.txt
external_user_local-0.0.33.dist-info/RECORD
