Metadata-Version: 2.1
Name: external-user-local
Version: 0.0.33
Home-page: https://github.com/circles-zone/external-user-local-python-package
Author: Circles
Author-email: info@circles.life
Classifier: Programming Language :: Python :: 3
Classifier: License :: Other/Proprietary License
Classifier: Operating System :: OS Independent
Requires-Dist: logger-local >=0.0.60
Requires-Dist: database-without-orm-local >=0.0.83
